celldega/__init__.py
celldega/clust/__init__.py
celldega/clust/constants.py
celldega/clust/matrix.py
celldega/clust/utils.py
celldega/nbhd/__init__.py
celldega/nbhd/alpha_shapes.py
celldega/nbhd/gradient.py
celldega/nbhd/hextile.py
celldega/nbhd/neighborhoods.py
celldega/nbhd/test_hextile.py
celldega/nbhd/utils.py
celldega/nbhd/zonal_stats.py
celldega/pre/__init__.py
celldega/pre/boundary_tile.py
celldega/pre/image_info.py
celldega/pre/landscape.py
celldega/pre/run_pre_processing.py
celldega/pre/sbg_tile.py
celldega/pre/trx_tile.py
celldega/qc/__init__.py
celldega/static/widget.css
celldega/static/widget.js
celldega/viz/__init__.py
celldega/viz/local_server.py
celldega/viz/widget.py
celldega-0.14.4.dist-info/METADATA
celldega-0.14.4.dist-info/WHEEL
celldega-0.14.4.dist-info/licenses/LICENSE.txt
celldega-0.14.4.dist-info/RECORD
