Metadata-Version: 2.3
Name: celldega
Version: 0.14.4
Requires-Dist: anndata~=0.11.0
Requires-Dist: anywidget~=0.9.18
Requires-Dist: dask~=2024.11.0
Requires-Dist: geopandas~=0.14.0
Requires-Dist: igraph~=0.11.8
Requires-Dist: imagecodecs
Requires-Dist: ipykernel
Requires-Dist: ipywidgets>=8.0.0
Requires-Dist: jupyterlab-widgets>=3.0.0
Requires-Dist: jupyterlab>=4.0
Requires-Dist: leidenalg~=0.10.2
Requires-Dist: libpysal~=4.8.0
Requires-Dist: matplotlib
Requires-Dist: mudata==0.3.1
Requires-Dist: muon==0.1.7
Requires-Dist: pandas~=2.2.0
Requires-Dist: polars~=1.10.0
Requires-Dist: pyarrow
Requires-Dist: rasterio==1.4.3
Requires-Dist: scanpy~=1.10.0
Requires-Dist: shapely~=2.0.0
Requires-Dist: spatialdata
Requires-Dist: spatialdata-io~=0.1.0
Requires-Dist: squidpy~=1.6.0
Requires-Dist: statsmodels~=0.14.5
Requires-Dist: tifffile~=2024.4.0
Requires-Dist: watchfiles
Requires-Dist: zarr~=2.17.0; python_version < '3.11'
Requires-Dist: zarr~=2.18.3; python_version >= '3.11'
Provides-Extra: dev
Requires-Dist: build; extra == 'dev'
Requires-Dist: mkdocs; extra == 'dev'
Requires-Dist: mkdocs-jupyter; extra == 'dev'
Requires-Dist: mkdocs-material; extra == 'dev'
Requires-Dist: mkdocs-open-in-new-tab; extra == 'dev'
Requires-Dist: mkdocstrings[javascript]; extra == 'dev'
Requires-Dist: mkdocstrings[python]; extra == 'dev'
Requires-Dist: pre-commit; extra == 'dev'
Requires-Dist: pytest; extra == 'dev'
Requires-Dist: pytest-cov; extra == 'dev'
Requires-Dist: pytest-html; extra == 'dev'
Requires-Dist: pytest-mock; extra == 'dev'
Requires-Dist: ruff; extra == 'dev'
Requires-Dist: twine; extra == 'dev'
Provides-Extra: pre
Requires-Dist: pyvips~=2.2.2; extra == 'pre'
